powerplanner/__init__.py
powerplanner/api_client.py
powerplanner/hub.py
powerplanner/models.py
powerplanner/__pycache__/__init__.cpython-311.pyc
powerplanner/__pycache__/api_client.cpython-311.pyc
powerplanner/__pycache__/hub.cpython-311.pyc
powerplanner_lib-0.0.15.dist-info/LICENSE
powerplanner_lib-0.0.15.dist-info/METADATA
powerplanner_lib-0.0.15.dist-info/WHEEL
powerplanner_lib-0.0.15.dist-info/top_level.txt
powerplanner_lib-0.0.15.dist-info/RECORD
