Metadata-Version: 2.1
Name: powerplanner-lib
Version: 0.0.15
Summary: Client package to access powerplanner API
Home-page: https://github.com/gurgelx/powerplanner_lib
Author: Gustaf Brahme
Classifier: Programming Language :: Python :: 3
Classifier: License :: OSI Approved :: MIT License
Classifier: Operating System :: OS Independent
License-File: LICENSE
Requires-Dist: aiohttp
Requires-Dist: aiozoneinfo
Requires-Dist: datetime
